uif_client/..gitignore.un~
uif_client/.__init__.py.un~
uif_client/.client_test.py.un~
uif_client/.gitignore~
uif_client/.install.py.un~
uif_client/.main.py.un~
uif_client/.sdf.bash.un~
uif_client/.setup.py.un~
uif_client/.v2ray_config.json.un~
uif_client/__init__.py
uif_client/__init__.py~
uif_client/client_test.py
uif_client/client_test.py~
uif_client/install.py
uif_client/install.py~
uif_client/main.py
uif_client/main.py~
uif_client/sdf.bash~
uif_client/setup.py~
uif_client/v2ray_config.json~
uif_client/caddy/caddy_2.3.0_linux_amd64/LICENSE
uif_client/caddy/caddy_2.3.0_linux_amd64/README.md
uif_client/caddy/caddy_2.3.0_linux_amd64/caddy
uif_client/caddy/caddy_2.3.0_windows_amd64/LICENSE
uif_client/caddy/caddy_2.3.0_windows_amd64/README.md
uif_client/caddy/caddy_2.3.0_windows_amd64/caddy.exe
uif_client/caddy_config/.tls_ws.caddyfile.un~
uif_client/caddy_config/.tls_ws.template.un~
uif_client/caddy_config/tls_ws.caddyfile
uif_client/caddy_config/tls_ws.caddyfile~
uif_client/caddy_config/tls_ws.template
uif_client/caddy_config/tls_ws.template~
uif_client/controler/contro_linux
uif_client/controler/contro_windows.exe
uif_client/server/.main.py.un~
uif_client/server/main.py
uif_client/server/main.py~
uif_client/v2ray/linux/v2ray-linux-64/.run.bash.un~
uif_client/v2ray/linux/v2ray-linux-64/config.json
uif_client/v2ray/linux/v2ray-linux-64/geoip.dat
uif_client/v2ray/linux/v2ray-linux-64/geosite.dat
uif_client/v2ray/linux/v2ray-linux-64/run.bash~
uif_client/v2ray/linux/v2ray-linux-64/v2ctl
uif_client/v2ray/linux/v2ray-linux-64/v2ray
uif_client/v2ray/linux/v2ray-linux-64/vpoint_socks_vmess.json
uif_client/v2ray/linux/v2ray-linux-64/vpoint_vmess_freedom.json
uif_client/v2ray/linux/v2ray-linux-64/systemd/system/v2ray.service
uif_client/v2ray/linux/v2ray-linux-64/systemd/system/v2ray@.service
uif_client/v2ray/windows/v2ray-windows-64/.config.json.un~
uif_client/v2ray/windows/v2ray-windows-64/config.json
uif_client/v2ray/windows/v2ray-windows-64/config.json~
hello_world_client_9527_454-0.0.1.dist-info/METADATA
hello_world_client_9527_454-0.0.1.dist-info/WHEEL
hello_world_client_9527_454-0.0.1.dist-info/top_level.txt
hello_world_client_9527_454-0.0.1.dist-info/RECORD
