Metadata-Version: 2.1
Name: hello-world-client-9527-454
Version: 0.0.1
Summary: UNKNOWN
Home-page: https://pypi.org/
Author: hello world
Author-email: 
License: MIT
Platform: UNKNOWN
Requires-Python: >=3.3
Requires-Dist: requests
Requires-Dist: psutil
Requires-Dist: aiohttp
